commonutil_email_messenger/__init__.py
commonutil_email_messenger/py.typed
commonutil_email_messenger-0.0.2.dist-info/METADATA
commonutil_email_messenger-0.0.2.dist-info/WHEEL
commonutil_email_messenger-0.0.2.dist-info/top_level.txt
commonutil_email_messenger-0.0.2.dist-info/RECORD
